toga_android/__init__.py
toga_android/app.py
toga_android/colors.py
toga_android/command.py
toga_android/container.py
toga_android/dialogs.py
toga_android/factory.py
toga_android/fonts.py
toga_android/icons.py
toga_android/images.py
toga_android/keys.py
toga_android/paths.py
toga_android/screens.py
toga_android/statusicons.py
toga_android/window.py
toga_android/hardware/__init__.py
toga_android/hardware/camera.py
toga_android/hardware/location.py
toga_android/libs/__init__.py
toga_android/libs/events.py
toga_android/resources/marker.png
toga_android/resources/optioncontainer-tab.png
toga_android/resources/toga.png
toga_android/widgets/__init__.py
toga_android/widgets/base.py
toga_android/widgets/box.py
toga_android/widgets/button.py
toga_android/widgets/canvas.py
toga_android/widgets/dateinput.py
toga_android/widgets/detailedlist.py
toga_android/widgets/divider.py
toga_android/widgets/imageview.py
toga_android/widgets/label.py
toga_android/widgets/mapview.py
toga_android/widgets/multilinetextinput.py
toga_android/widgets/numberinput.py
toga_android/widgets/optioncontainer.py
toga_android/widgets/passwordinput.py
toga_android/widgets/progressbar.py
toga_android/widgets/scrollcontainer.py
toga_android/widgets/selection.py
toga_android/widgets/slider.py
toga_android/widgets/switch.py
toga_android/widgets/table.py
toga_android/widgets/textinput.py
toga_android/widgets/timeinput.py
toga_android/widgets/webview.py
toga_android/widgets/internal/__init__.py
toga_android/widgets/internal/pickers.py
toga_android-0.5.2.dist-info/licenses/LICENSE
toga_android-0.5.2.dist-info/METADATA
toga_android-0.5.2.dist-info/WHEEL
toga_android-0.5.2.dist-info/entry_points.txt
toga_android-0.5.2.dist-info/top_level.txt
toga_android-0.5.2.dist-info/RECORD
